paravastulab/__init__.py
paravastulab/core.py
paravastulab-0.1.0.dist-info/LICENSE
paravastulab-0.1.0.dist-info/METADATA
paravastulab-0.1.0.dist-info/WHEEL
paravastulab-0.1.0.dist-info/top_level.txt
paravastulab-0.1.0.dist-info/RECORD
