Metadata-Version: 2.1
Name: paravastulab
Version: 0.1.0
Summary: A utility package for handling files and paths, particularly with Dropbox integration.
Author: Daniel
Author-email: dmd9@gatech.edu
License: MIT
Classifier: Programming Language :: Python :: 3
Classifier: License :: OSI Approved :: MIT License
Classifier: Operating System :: OS Independent
Requires-Python: >=3.6
License-File: LICENSE
Requires-Dist: ipywidgets
Requires-Dist: numpy
Requires-Dist: ipython
